MANIFEST.in
README.txt
setup.py
c2/__init__.py
c2.app.fbpage.egg-info/PKG-INFO
c2.app.fbpage.egg-info/SOURCES.txt
c2.app.fbpage.egg-info/dependency_links.txt
c2.app.fbpage.egg-info/entry_points.txt
c2.app.fbpage.egg-info/namespace_packages.txt
c2.app.fbpage.egg-info/not-zip-safe
c2.app.fbpage.egg-info/requires.txt
c2.app.fbpage.egg-info/top_level.txt
c2/app/__init__.py
c2/app/fbpage/__init__.py
c2/app/fbpage/configure.zcml
c2/app/fbpage/tests.py
c2/app/fbpage/version.txt
c2/app/fbpage/browser/__init__.py
c2/app/fbpage/browser/base.pt
c2/app/fbpage/browser/configure.zcml
c2/app/fbpage/browser/listing.pt
c2/app/fbpage/browser/listing.py
c2/app/fbpage/browser/ngibloglist.pt
c2/app/fbpage/browser/ngibloglist.py
c2/app/fbpage/browser/resources/style.css
c2/app/fbpage/profiles/default/metadata.xml
docs/HISTORY.txt
docs/INSTALL.txt
docs/LICENSE.GPL
docs/LICENSE.txt