Metadata-Version: 1.0
Name: c2.app.fbpage
Version: 1.0b1
Summary: UNKNOWN
Home-page: http://www.cmscom.jp
Author: Manabu TERADA
Author-email: terada@cmscom.jp
License: GPL
Keywords: plone facebook
Platform: UNKNOWN
Classifier: Framework :: Plone
Classifier: Programming Language :: Python
